{
  "timestamp": "2025-07-04T03:35:30.764Z",
  "reports": [
    {
      "url": "https://adibfirman.dev/",
      "device": "mobile",
      "perf": 0.95,
      "fid": 0,
      "lcp": 924.03,
      "cls": 0,
      "fcp": 924.03,
      "fci": 0,
      "tbt": 44.5,
      "tti": 2735.12,
      "si": 5813.78,
      "req": 19,
      "size": 260285
    },
    {
      "url": "https://adibfirman.dev/",
      "device": "desktop",
      "perf": 1,
      "fid": 0,
      "lcp": 332,
      "cls": 0,
      "fcp": 259,
      "fci": 0,
      "tbt": 9.5,
      "tti": 695,
      "si": 602.11,
      "req": 30,
      "size": 315295
    },
    {
      "url": "https://adibfirman.dev/blog/",
      "device": "mobile",
      "perf": 0.98,
      "fid": 0,
      "lcp": 1144.41,
      "cls": 0,
      "fcp": 1144.41,
      "fci": 0,
      "tbt": 125,
      "tti": 3613.13,
      "si": 2445.32,
      "req": 22,
      "size": 280615
    },
    {
      "url": "https://adibfirman.dev/blog/",
      "device": "desktop",
      "perf": 1,
      "fid": 0,
      "lcp": 310.13,
      "cls": 0.00311,
      "fcp": 310.13,
      "fci": 0,
      "tbt": 18,
      "tti": 917.39,
      "si": 1109.08,
      "req": 33,
      "size": 335649
    },
    {
      "url": "https://adibfirman.dev/blog/context-api-in-react",
      "device": "mobile",
      "perf": 0.84,
      "fid": 0,
      "lcp": 3160.24,
      "cls": 0.10682,
      "fcp": 937.24,
      "fci": 0,
      "tbt": 278.66,
      "tti": 5044.76,
      "si": 3234.22,
      "req": 26,
      "size": 615984
    },
    {
      "url": "https://adibfirman.dev/blog/context-api-in-react",
      "device": "desktop",
      "perf": 0.84,
      "fid": 0,
      "lcp": 791.08,
      "cls": 0.10112,
      "fcp": 671.08,
      "fci": 0,
      "tbt": 299.96,
      "tti": 1319.42,
      "si": 882.72,
      "req": 35,
      "size": 655435
    }
  ]
}