{
  "timestamp": "2022-08-23T04:29:02.054Z",
  "reports": [
    {
      "url": "https://adibfirman.dev/",
      "device": "mobile",
      "perf": 0.71,
      "fid": 0,
      "lcp": 1000,
      "cls": 0,
      "fcp": 1000,
      "fci": 0,
      "tbt": 978,
      "tti": 5190,
      "si": 5486.37,
      "req": 27,
      "size": 429992
    },
    {
      "url": "https://adibfirman.dev/",
      "device": "desktop",
      "perf": 0.96,
      "fid": 0,
      "lcp": 426,
      "cls": 0,
      "fcp": 299,
      "fci": 0,
      "tbt": 159,
      "tti": 1223,
      "si": 485.92,
      "req": 38,
      "size": 481219
    },
    {
      "url": "https://adibfirman.dev/blog/",
      "device": "mobile",
      "perf": 0.73,
      "fid": 0,
      "lcp": 1343,
      "cls": 0.0484,
      "fcp": 1165,
      "fci": 0,
      "tbt": 1102,
      "tti": 6100.5,
      "si": 1493.24,
      "req": 30,
      "size": 441931
    },
    {
      "url": "https://adibfirman.dev/blog/",
      "device": "desktop",
      "perf": 0.94,
      "fid": 0,
      "lcp": 636,
      "cls": 0.02286,
      "fcp": 359,
      "fci": 0,
      "tbt": 143,
      "tti": 1790.5,
      "si": 1760.71,
      "req": 39,
      "size": 486086
    },
    {
      "url": "https://adibfirman.dev/blog/context-api-in-react",
      "device": "mobile",
      "perf": 0.62,
      "fid": 0,
      "lcp": 1860,
      "cls": 0.0326,
      "fcp": 1860,
      "fci": 0,
      "tbt": 2925,
      "tti": 7508,
      "si": 3890.74,
      "req": 29,
      "size": 492211
    },
    {
      "url": "https://adibfirman.dev/blog/context-api-in-react",
      "device": "desktop",
      "perf": 0.7,
      "fid": 0,
      "lcp": 540,
      "cls": 0.09159,
      "fcp": 540,
      "fci": 0,
      "tbt": 762,
      "tti": 1834,
      "si": 1467.61,
      "req": 40,
      "size": 543451
    }
  ]
}