{
  "timestamp": "2024-12-08T03:24:28.348Z",
  "reports": [
    {
      "url": "https://adibfirman.dev/",
      "device": "mobile",
      "perf": 0.9,
      "fid": 0,
      "lcp": 922.03,
      "cls": 0.13187,
      "fcp": 922.03,
      "fci": 0,
      "tbt": 101,
      "tti": 3280.62,
      "si": 5645.68,
      "req": 19,
      "size": 259462
    },
    {
      "url": "https://adibfirman.dev/",
      "device": "desktop",
      "perf": 0.96,
      "fid": 0,
      "lcp": 286.02,
      "cls": 0,
      "fcp": 268.02,
      "fci": 0,
      "tbt": 172,
      "tti": 958.09,
      "si": 715.78,
      "req": 30,
      "size": 314015
    },
    {
      "url": "https://adibfirman.dev/blog/",
      "device": "mobile",
      "perf": 0.97,
      "fid": 0,
      "lcp": 1096.87,
      "cls": 0,
      "fcp": 1096.87,
      "fci": 0,
      "tbt": 186,
      "tti": 3421.34,
      "si": 2480.47,
      "req": 22,
      "size": 279957
    },
    {
      "url": "https://adibfirman.dev/blog/",
      "device": "desktop",
      "perf": 0.96,
      "fid": 0,
      "lcp": 538.75,
      "cls": 0.00311,
      "fcp": 321.37,
      "fci": 0,
      "tbt": 174.94,
      "tti": 1094.69,
      "si": 730.2,
      "req": 33,
      "size": 334501
    },
    {
      "url": "https://adibfirman.dev/blog/context-api-in-react",
      "device": "mobile",
      "perf": 0.68,
      "fid": 0,
      "lcp": 2572,
      "cls": 0.1034,
      "fcp": 1834.55,
      "fci": 0,
      "tbt": 1088,
      "tti": 5393,
      "si": 4069.55,
      "req": 26,
      "size": 443200
    },
    {
      "url": "https://adibfirman.dev/blog/context-api-in-react",
      "device": "desktop",
      "perf": 0.77,
      "fid": 0,
      "lcp": 485.55,
      "cls": 0.09366,
      "fcp": 485.55,
      "fci": 0,
      "tbt": 478,
      "tti": 1452.1,
      "si": 943.5,
      "req": 35,
      "size": 482263
    }
  ]
}