{
  "timestamp": "2022-05-04T03:39:39.228Z",
  "reports": [
    {
      "url": "https://adibfirman.dev/",
      "device": "mobile",
      "perf": 0.73,
      "fid": 0,
      "lcp": 1016,
      "cls": 0,
      "fcp": 1016,
      "fci": 0,
      "tbt": 966,
      "tti": 5077,
      "si": 4811.45,
      "req": 28,
      "size": 434732
    },
    {
      "url": "https://adibfirman.dev/",
      "device": "desktop",
      "perf": 0.96,
      "fid": 0,
      "lcp": 550,
      "cls": 0,
      "fcp": 293,
      "fci": 0,
      "tbt": 160,
      "tti": 1210,
      "si": 471.26,
      "req": 39,
      "size": 483602
    },
    {
      "url": "https://adibfirman.dev/blog/",
      "device": "mobile",
      "perf": 0.69,
      "fid": 0,
      "lcp": 1770,
      "cls": 0.10677,
      "fcp": 1181,
      "fci": 0,
      "tbt": 1208,
      "tti": 6632,
      "si": 2159.2,
      "req": 31,
      "size": 466203
    },
    {
      "url": "https://adibfirman.dev/blog/",
      "device": "desktop",
      "perf": 0.97,
      "fid": 0,
      "lcp": 616,
      "cls": 0.11431,
      "fcp": 350,
      "fci": 0,
      "tbt": 101.5,
      "tti": 1772.5,
      "si": 388.6,
      "req": 40,
      "size": 509503
    },
    {
      "url": "https://adibfirman.dev/blog/memahami-apa-itu-snowpack",
      "device": "mobile",
      "perf": 0.52,
      "fid": 0,
      "lcp": 2310,
      "cls": 0.01035,
      "fcp": 2310,
      "fci": 0,
      "tbt": 7911,
      "tti": 13782.5,
      "si": 5768.85,
      "req": 35,
      "size": 1810640
    },
    {
      "url": "https://adibfirman.dev/blog/memahami-apa-itu-snowpack",
      "device": "desktop",
      "perf": 0.78,
      "fid": 0,
      "lcp": 620,
      "cls": 0.03314,
      "fcp": 620,
      "fci": 0,
      "tbt": 487,
      "tti": 1587,
      "si": 958.63,
      "req": 46,
      "size": 1859497
    }
  ]
}