{
  "timestamp": "2023-07-16T03:18:23.409Z",
  "reports": [
    {
      "url": "https://adibfirman.dev/",
      "device": "mobile",
      "perf": 0.76,
      "fid": 0,
      "lcp": 1086,
      "cls": 0,
      "fcp": 1086,
      "fci": 0,
      "tbt": 788.5,
      "tti": 4554.5,
      "si": 5776.66,
      "req": 24,
      "size": 411921
    },
    {
      "url": "https://adibfirman.dev/",
      "device": "desktop",
      "perf": 0.98,
      "fid": 0,
      "lcp": 718,
      "cls": 0,
      "fcp": 407,
      "fci": 0,
      "tbt": 113,
      "tti": 982,
      "si": 767.66,
      "req": 37,
      "size": 474795
    },
    {
      "url": "https://adibfirman.dev/blog/",
      "device": "mobile",
      "perf": 0.64,
      "fid": 0,
      "lcp": 1320,
      "cls": 0.27582,
      "fcp": 1320,
      "fci": 0,
      "tbt": 999.5,
      "tti": 6180.5,
      "si": 2461.89,
      "req": 27,
      "size": 432924
    },
    {
      "url": "https://adibfirman.dev/blog/",
      "device": "desktop",
      "perf": 0.98,
      "fid": 0,
      "lcp": 346,
      "cls": 0,
      "fcp": 346,
      "fci": 0,
      "tbt": 106,
      "tti": 1385,
      "si": 1053.05,
      "req": 40,
      "size": 493396
    },
    {
      "url": "https://adibfirman.dev/blog/context-api-in-react",
      "device": "mobile",
      "perf": 0.65,
      "fid": 0,
      "lcp": 1836,
      "cls": 0.1034,
      "fcp": 1836,
      "fci": 0,
      "tbt": 2805,
      "tti": 7513,
      "si": 3582.92,
      "req": 31,
      "size": 592457
    },
    {
      "url": "https://adibfirman.dev/blog/context-api-in-react",
      "device": "desktop",
      "perf": 0.74,
      "fid": 0,
      "lcp": 596.5,
      "cls": 0.09159,
      "fcp": 508.5,
      "fci": 0,
      "tbt": 585,
      "tti": 1643.5,
      "si": 983.77,
      "req": 42,
      "size": 640229
    }
  ]
}