{
  "timestamp": "2025-03-13T03:10:31.820Z",
  "reports": [
    {
      "url": "https://adibfirman.dev/",
      "device": "mobile",
      "perf": 0.9,
      "fid": 0,
      "lcp": 917.06,
      "cls": 0.13187,
      "fcp": 917.06,
      "fci": 0,
      "tbt": 9,
      "tti": 2676.3,
      "si": 5945.22,
      "req": 19,
      "size": 260170
    },
    {
      "url": "https://adibfirman.dev/",
      "device": "desktop",
      "perf": 1,
      "fid": 0,
      "lcp": 268.07,
      "cls": 0,
      "fcp": 268.07,
      "fci": 0,
      "tbt": 44.5,
      "tti": 743.21,
      "si": 930.21,
      "req": 30,
      "size": 315142
    },
    {
      "url": "https://adibfirman.dev/blog/",
      "device": "mobile",
      "perf": 0.97,
      "fid": 0,
      "lcp": 1283.42,
      "cls": 0,
      "fcp": 1126.35,
      "fci": 0,
      "tbt": 185.5,
      "tti": 3631.21,
      "si": 2195.25,
      "req": 22,
      "size": 280816
    },
    {
      "url": "https://adibfirman.dev/blog/",
      "device": "desktop",
      "perf": 0,
      "fid": 0,
      "lcp": 0,
      "cls": 0,
      "fcp": 0,
      "fci": 0,
      "tbt": 0,
      "tti": 0,
      "si": 0,
      "req": 0,
      "size": 0
    },
    {
      "url": "https://adibfirman.dev/blog/context-api-in-react",
      "device": "mobile",
      "perf": 0.78,
      "fid": 0,
      "lcp": 2703.08,
      "cls": 0.10557,
      "fcp": 2703.08,
      "fci": 0,
      "tbt": 387,
      "tti": 5175.09,
      "si": 4017.26,
      "req": 26,
      "size": 616136
    },
    {
      "url": "https://adibfirman.dev/blog/context-api-in-react",
      "device": "desktop",
      "perf": 0.89,
      "fid": 0,
      "lcp": 642.12,
      "cls": 0.10112,
      "fcp": 642.12,
      "fci": 0,
      "tbt": 221.92,
      "tti": 1243.59,
      "si": 1025.57,
      "req": 35,
      "size": 655591
    }
  ]
}