{
  "timestamp": "2022-12-23T02:50:31.981Z",
  "reports": [
    {
      "url": "https://adibfirman.dev/",
      "device": "mobile",
      "perf": 0.78,
      "fid": 0,
      "lcp": 1005,
      "cls": 0.12709,
      "fcp": 1005,
      "fci": 0,
      "tbt": 559,
      "tti": 4224,
      "si": 5119.31,
      "req": 22,
      "size": 310655
    },
    {
      "url": "https://adibfirman.dev/",
      "device": "desktop",
      "perf": 0.97,
      "fid": 0,
      "lcp": 663,
      "cls": 0,
      "fcp": 301,
      "fci": 0,
      "tbt": 147,
      "tti": 923,
      "si": 650.94,
      "req": 35,
      "size": 373540
    },
    {
      "url": "https://adibfirman.dev/blog/",
      "device": "mobile",
      "perf": 0.65,
      "fid": 0,
      "lcp": 1341,
      "cls": 0.35156,
      "fcp": 1174,
      "fci": 0,
      "tbt": 970.5,
      "tti": 5458.5,
      "si": 1655.61,
      "req": 25,
      "size": 326463
    },
    {
      "url": "https://adibfirman.dev/blog/",
      "device": "desktop",
      "perf": 0.99,
      "fid": 0,
      "lcp": 668,
      "cls": 0.04869,
      "fcp": 349,
      "fci": 0,
      "tbt": 75,
      "tti": 1167.5,
      "si": 890.53,
      "req": 36,
      "size": 384498
    },
    {
      "url": "https://adibfirman.dev/blog/context-api-in-react",
      "device": "mobile",
      "perf": 0.62,
      "fid": 0,
      "lcp": 1860,
      "cls": 0.0326,
      "fcp": 1860,
      "fci": 0,
      "tbt": 3139,
      "tti": 7882,
      "si": 3778.14,
      "req": 29,
      "size": 492422
    },
    {
      "url": "https://adibfirman.dev/blog/context-api-in-react",
      "device": "desktop",
      "perf": 0.68,
      "fid": 0,
      "lcp": 540,
      "cls": 0.09159,
      "fcp": 540,
      "fci": 0,
      "tbt": 1044,
      "tti": 2139,
      "si": 1340.14,
      "req": 40,
      "size": 540227
    }
  ]
}