{
  "timestamp": "2023-12-17T02:41:58.547Z",
  "reports": [
    {
      "url": "https://adibfirman.dev/",
      "device": "mobile",
      "perf": 0.75,
      "fid": 0,
      "lcp": 1196.5,
      "cls": 0.13187,
      "fcp": 1196.5,
      "fci": 0,
      "tbt": 601,
      "tti": 3997,
      "si": 5500.8,
      "req": 0,
      "size": 0
    },
    {
      "url": "https://adibfirman.dev/",
      "device": "desktop",
      "perf": 0.99,
      "fid": 0,
      "lcp": 568,
      "cls": 0,
      "fcp": 568,
      "fci": 0,
      "tbt": 60.5,
      "tti": 1072.5,
      "si": 1085.85,
      "req": 0,
      "size": 0
    },
    {
      "url": "https://adibfirman.dev/blog/",
      "device": "mobile",
      "perf": 0.78,
      "fid": 0,
      "lcp": 1419.5,
      "cls": 0,
      "fcp": 1206.58,
      "fci": 0,
      "tbt": 1015.62,
      "tti": 4905.75,
      "si": 2040.92,
      "req": 0,
      "size": 0
    },
    {
      "url": "https://adibfirman.dev/blog/",
      "device": "desktop",
      "perf": 0.86,
      "fid": 0,
      "lcp": 589.29,
      "cls": 0,
      "fcp": 385.05,
      "fci": 0,
      "tbt": 317,
      "tti": 1659.4,
      "si": 875.07,
      "req": 0,
      "size": 0
    },
    {
      "url": "https://adibfirman.dev/blog/context-api-in-react",
      "device": "mobile",
      "perf": 0.66,
      "fid": 0,
      "lcp": 1835,
      "cls": 0.1034,
      "fcp": 1835,
      "fci": 0,
      "tbt": 2315,
      "tti": 6395,
      "si": 3270.91,
      "req": 0,
      "size": 0
    },
    {
      "url": "https://adibfirman.dev/blog/context-api-in-react",
      "device": "desktop",
      "perf": 0.8,
      "fid": 0,
      "lcp": 587,
      "cls": 0.09159,
      "fcp": 587,
      "fci": 0,
      "tbt": 396.5,
      "tti": 1499.5,
      "si": 1008.62,
      "req": 0,
      "size": 0
    }
  ]
}