{
  "timestamp": "2023-11-15T02:40:04.828Z",
  "reports": [
    {
      "url": "https://adibfirman.dev/",
      "device": "mobile",
      "perf": 0.76,
      "fid": 0,
      "lcp": 1207.5,
      "cls": 0,
      "fcp": 1207.5,
      "fci": 0,
      "tbt": 749.5,
      "tti": 4044.5,
      "si": 6014.89,
      "req": 0,
      "size": 0
    },
    {
      "url": "https://adibfirman.dev/",
      "device": "desktop",
      "perf": 0.98,
      "fid": 0,
      "lcp": 476,
      "cls": 0,
      "fcp": 461,
      "fci": 0,
      "tbt": 129,
      "tti": 1168,
      "si": 678.85,
      "req": 0,
      "size": 0
    },
    {
      "url": "https://adibfirman.dev/blog/",
      "device": "mobile",
      "perf": 0.74,
      "fid": 0,
      "lcp": 1199.14,
      "cls": 0,
      "fcp": 1199.14,
      "fci": 0,
      "tbt": 1468,
      "tti": 5503.12,
      "si": 2044.28,
      "req": 0,
      "size": 0
    },
    {
      "url": "https://adibfirman.dev/blog/",
      "device": "desktop",
      "perf": 0.91,
      "fid": 0,
      "lcp": 576.69,
      "cls": 0.07838,
      "fcp": 576.69,
      "fci": 0,
      "tbt": 207,
      "tti": 2645.99,
      "si": 1152.2,
      "req": 0,
      "size": 0
    },
    {
      "url": "https://adibfirman.dev/blog/context-api-in-react",
      "device": "mobile",
      "perf": 0.59,
      "fid": 0,
      "lcp": 1836,
      "cls": 0.1034,
      "fcp": 1836,
      "fci": 0,
      "tbt": 3609,
      "tti": 7349,
      "si": 7132.92,
      "req": 0,
      "size": 0
    },
    {
      "url": "https://adibfirman.dev/blog/context-api-in-react",
      "device": "desktop",
      "perf": 0.72,
      "fid": 0,
      "lcp": 516,
      "cls": 0.09159,
      "fcp": 516,
      "fci": 0,
      "tbt": 730.5,
      "tti": 1632.5,
      "si": 1046.62,
      "req": 0,
      "size": 0
    }
  ]
}