{
  "timestamp": "2025-01-17T02:56:31.981Z",
  "reports": [
    {
      "url": "https://adibfirman.dev/",
      "device": "mobile",
      "perf": 0.95,
      "fid": 0,
      "lcp": 917.02,
      "cls": 0,
      "fcp": 917.02,
      "fci": 0,
      "tbt": 71.5,
      "tti": 3270.61,
      "si": 5402.19,
      "req": 19,
      "size": 260112
    },
    {
      "url": "https://adibfirman.dev/",
      "device": "desktop",
      "perf": 1,
      "fid": 0,
      "lcp": 261.04,
      "cls": 0,
      "fcp": 261.04,
      "fci": 0,
      "tbt": 40.5,
      "tti": 731.12,
      "si": 892.09,
      "req": 30,
      "size": 315084
    },
    {
      "url": "https://adibfirman.dev/blog/",
      "device": "mobile",
      "perf": 0.92,
      "fid": 0,
      "lcp": 1093.01,
      "cls": 0,
      "fcp": 1093.01,
      "fci": 0,
      "tbt": 328.5,
      "tti": 3818.64,
      "si": 2112.21,
      "req": 22,
      "size": 280753
    },
    {
      "url": "https://adibfirman.dev/blog/",
      "device": "desktop",
      "perf": 0.75,
      "fid": 0,
      "lcp": 309.7,
      "cls": 0.21689,
      "fcp": 309.7,
      "fci": 0,
      "tbt": 324,
      "tti": 1157.97,
      "si": 931.51,
      "req": 33,
      "size": 335851
    },
    {
      "url": "https://adibfirman.dev/blog/context-api-in-react",
      "device": "mobile",
      "perf": 0.7,
      "fid": 0,
      "lcp": 2014,
      "cls": 0.1034,
      "fcp": 1806.52,
      "fci": 0,
      "tbt": 1181,
      "tti": 5576.5,
      "si": 4111.09,
      "req": 26,
      "size": 443978
    },
    {
      "url": "https://adibfirman.dev/blog/context-api-in-react",
      "device": "desktop",
      "perf": 0.66,
      "fid": 0,
      "lcp": 664,
      "cls": 0.11343,
      "fcp": 485.54,
      "fci": 0,
      "tbt": 1004,
      "tti": 1938,
      "si": 1522.29,
      "req": 35,
      "size": 483441
    }
  ]
}