{
  "timestamp": "2023-01-30T02:51:10.146Z",
  "reports": [
    {
      "url": "https://adibfirman.dev/",
      "device": "mobile",
      "perf": 0.64,
      "fid": 0,
      "lcp": 2151,
      "cls": 0.12709,
      "fcp": 1168,
      "fci": 0,
      "tbt": 1269.5,
      "tti": 5039.5,
      "si": 5872.42,
      "req": 22,
      "size": 311021
    },
    {
      "url": "https://adibfirman.dev/",
      "device": "desktop",
      "perf": 0.96,
      "fid": 0,
      "lcp": 639,
      "cls": 0,
      "fcp": 324,
      "fci": 0,
      "tbt": 153,
      "tti": 1013,
      "si": 647.71,
      "req": 35,
      "size": 373919
    },
    {
      "url": "https://adibfirman.dev/blog/",
      "device": "mobile",
      "perf": 0.76,
      "fid": 0,
      "lcp": 1339,
      "cls": 0,
      "fcp": 1167,
      "fci": 0,
      "tbt": 909,
      "tti": 5478.5,
      "si": 1659.72,
      "req": 25,
      "size": 329127
    },
    {
      "url": "https://adibfirman.dev/blog/",
      "device": "desktop",
      "perf": 0.98,
      "fid": 0,
      "lcp": 669,
      "cls": 0,
      "fcp": 356,
      "fci": 0,
      "tbt": 108,
      "tti": 1433,
      "si": 789.06,
      "req": 36,
      "size": 387171
    },
    {
      "url": "https://adibfirman.dev/blog/context-api-in-react",
      "device": "mobile",
      "perf": 0.6,
      "fid": 0,
      "lcp": 1860,
      "cls": 0.0326,
      "fcp": 1860,
      "fci": 0,
      "tbt": 4080,
      "tti": 8609,
      "si": 4518.88,
      "req": 29,
      "size": 492153
    },
    {
      "url": "https://adibfirman.dev/blog/context-api-in-react",
      "device": "desktop",
      "perf": 0.71,
      "fid": 0,
      "lcp": 540,
      "cls": 0.09159,
      "fcp": 540,
      "fci": 0,
      "tbt": 778,
      "tti": 1818,
      "si": 1181.12,
      "req": 40,
      "size": 539956
    }
  ]
}