{
  "timestamp": "2022-02-08T02:48:54.600Z",
  "reports": [
    {
      "url": "https://adibfirman.dev/",
      "device": "mobile",
      "perf": 0.7,
      "fid": 0,
      "lcp": 1903,
      "cls": 0,
      "fcp": 1073,
      "fci": 0,
      "tbt": 1593.5,
      "tti": 5457.5,
      "si": 1970.6,
      "req": 31,
      "size": 437171
    },
    {
      "url": "https://adibfirman.dev/",
      "device": "desktop",
      "perf": 1,
      "fid": 0,
      "lcp": 476,
      "cls": 0,
      "fcp": 289,
      "fci": 0,
      "tbt": 60.5,
      "tti": 1116.5,
      "si": 488.02,
      "req": 43,
      "size": 524584
    },
    {
      "url": "https://adibfirman.dev/blog/",
      "device": "mobile",
      "perf": 0.73,
      "fid": 0,
      "lcp": 1290,
      "cls": 0,
      "fcp": 1213,
      "fci": 0,
      "tbt": 1140,
      "tti": 6084,
      "si": 1292.17,
      "req": 34,
      "size": 472638
    },
    {
      "url": "https://adibfirman.dev/blog/",
      "device": "desktop",
      "perf": 0.89,
      "fid": 0,
      "lcp": 620,
      "cls": 0,
      "fcp": 383,
      "fci": 0,
      "tbt": 276,
      "tti": 1999,
      "si": 541.26,
      "req": 49,
      "size": 567222
    },
    {
      "url": "https://adibfirman.dev/blog/memahami-apa-itu-snowpack",
      "device": "mobile",
      "perf": 0.52,
      "fid": 0,
      "lcp": 2310,
      "cls": 0.0244,
      "fcp": 2310,
      "fci": 0,
      "tbt": 9172.5,
      "tti": 14644,
      "si": 5675.79,
      "req": 34,
      "size": 1800136
    },
    {
      "url": "https://adibfirman.dev/blog/memahami-apa-itu-snowpack",
      "device": "desktop",
      "perf": 0.78,
      "fid": 0,
      "lcp": 620,
      "cls": 0.0279,
      "fcp": 620,
      "fci": 0,
      "tbt": 528,
      "tti": 1608,
      "si": 759.73,
      "req": 46,
      "size": 1887543
    }
  ]
}