{
  "timestamp": "2023-08-18T02:34:14.793Z",
  "reports": [
    {
      "url": "https://adibfirman.dev/",
      "device": "mobile",
      "perf": 0.69,
      "fid": 0,
      "lcp": 1125,
      "cls": 0.13187,
      "fcp": 1125,
      "fci": 0,
      "tbt": 885.5,
      "tti": 4745,
      "si": 6406.36,
      "req": 0,
      "size": 0
    },
    {
      "url": "https://adibfirman.dev/",
      "device": "desktop",
      "perf": 0.99,
      "fid": 0,
      "lcp": 669.5,
      "cls": 0,
      "fcp": 351,
      "fci": 0,
      "tbt": 75.25,
      "tti": 958.25,
      "si": 720.46,
      "req": 0,
      "size": 0
    },
    {
      "url": "https://adibfirman.dev/blog/",
      "device": "mobile",
      "perf": 0.82,
      "fid": 0,
      "lcp": 1196.89,
      "cls": 0,
      "fcp": 1196.89,
      "fci": 0,
      "tbt": 705,
      "tti": 5705.47,
      "si": 2332.54,
      "req": 0,
      "size": 0
    },
    {
      "url": "https://adibfirman.dev/blog/",
      "device": "desktop",
      "perf": 1,
      "fid": 0,
      "lcp": 689.42,
      "cls": 0,
      "fcp": 380.92,
      "fci": 0,
      "tbt": 52,
      "tti": 1479.47,
      "si": 678.34,
      "req": 0,
      "size": 0
    },
    {
      "url": "https://adibfirman.dev/blog/context-api-in-react",
      "device": "mobile",
      "perf": 0.65,
      "fid": 0,
      "lcp": 1837,
      "cls": 0.1034,
      "fcp": 1837,
      "fci": 0,
      "tbt": 2659,
      "tti": 7446,
      "si": 3661.87,
      "req": 0,
      "size": 0
    },
    {
      "url": "https://adibfirman.dev/blog/context-api-in-react",
      "device": "desktop",
      "perf": 0.71,
      "fid": 0,
      "lcp": 589.5,
      "cls": 0.09159,
      "fcp": 589.5,
      "fci": 0,
      "tbt": 769,
      "tti": 2020.5,
      "si": 1180.71,
      "req": 0,
      "size": 0
    }
  ]
}